README.md
setup.py
dockerplugin/__init__.py
dockerplugin/decorators.py
dockerplugin/discovery.py
dockerplugin/exceptions.py
dockerplugin/tasks.py
dockerplugin/utils.py
dockerplugin_fiberhome.egg-info/PKG-INFO
dockerplugin_fiberhome.egg-info/SOURCES.txt
dockerplugin_fiberhome.egg-info/dependency_links.txt
dockerplugin_fiberhome.egg-info/not-zip-safe
dockerplugin_fiberhome.egg-info/requires.txt
dockerplugin_fiberhome.egg-info/top_level.txt