Metadata-Version: 1.0
Name: dockerplugin-fiberhome
Version: 2.4.0
Summary: Cloudify plugin for applications run in Docker containers,revised by FiberHome
Home-page: UNKNOWN
Author: Michael Hwang, Tommy Carpenter,Minglu Li
Author-email: UNKNOWN
License: UNKNOWN
Platform: UNKNOWN
